yourbubble/__init__.py
yourbubble/messagerie.py
yourbubble/protocol.py
yourbubble-0.1.0.dist-info/licenses/LICENSE
yourbubble-0.1.0.dist-info/METADATA
yourbubble-0.1.0.dist-info/WHEEL
yourbubble-0.1.0.dist-info/entry_points.txt
yourbubble-0.1.0.dist-info/top_level.txt
yourbubble-0.1.0.dist-info/RECORD
