Metadata-Version: 2.4
Name: yourbubble
Version: 0.1.0
Summary: Ephemeral messaging over UDP — send, receive, vanish.
Author-email: takouzlo <f.bfalik@gmail.com>
License: MIT
Classifier: License :: OSI Approved :: MIT License
Classifier: Programming Language :: Python :: 3
Classifier: Topic :: Communications :: Chat
Classifier: Topic :: Security :: Cryptography
Classifier: Intended Audience :: End Users/Desktop
Requires-Python: >=3.8
License-File: LICENSE
Dynamic: license-file
